{ "_t" : "BH.oM.PlantRoomSizer.DataSeries", "DataPoints" : [{ "_t" : "BH.oM.PlantRoomSizer.CurvePoint", "X" : 600.0, "Y" : 11.216931216931217 }, { "_t" : "BH.oM.PlantRoomSizer.CurvePoint", "X" : 1000.0, "Y" : 12.20458553791887 }, { "_t" : "BH.oM.PlantRoomSizer.CurvePoint", "X" : 2000.0, "Y" : 15.943562610229275 }, { "_t" : "BH.oM.PlantRoomSizer.CurvePoint", "X" : 4000.0, "Y" : 19.25925925925926 }, { "_t" : "BH.oM.PlantRoomSizer.CurvePoint", "X" : 6000.0, "Y" : 21.869488536155202 }, { "_t" : "BH.oM.PlantRoomSizer.CurvePoint", "X" : 8000.0, "Y" : 26.031746031746032 }, { "_t" : "BH.oM.PlantRoomSizer.CurvePoint", "X" : 10000.0, "Y" : 29.1358024691358 }, { "_t" : "BH.oM.PlantRoomSizer.CurvePoint", "X" : 12000.0, "Y" : 33.298059964726633 }, { "_t" : "BH.oM.PlantRoomSizer.CurvePoint", "X" : 14000.0, "Y" : 34.638447971781304 }, { "_t" : "BH.oM.PlantRoomSizer.CurvePoint", "X" : 16000.0, "Y" : 34.920634920634917 }, { "_t" : "BH.oM.PlantRoomSizer.CurvePoint", "X" : 18000.0, "Y" : 36.19047619047619 }], "BHoM_Guid" : "efec6e37-cc79-43b6-8ea0-ac4c737c995b", "_bhomVersion" : "6.3" }