{ "_t" : "BH.oM.PlantRoomSizer.DataSeries", "DataPoints" : [{ "_t" : "BH.oM.PlantRoomSizer.CurvePoint", "X" : 92.0, "Y" : 2.7556818181818179 }, { "_t" : "BH.oM.PlantRoomSizer.CurvePoint", "X" : 130.0, "Y" : 2.7698863636363638 }, { "_t" : "BH.oM.PlantRoomSizer.CurvePoint", "X" : 180.0, "Y" : 2.8267045454545454 }, { "_t" : "BH.oM.PlantRoomSizer.CurvePoint", "X" : 230.0, "Y" : 2.8409090909090908 }, { "_t" : "BH.oM.PlantRoomSizer.CurvePoint", "X" : 290.0, "Y" : 2.8693181818181817 }, { "_t" : "BH.oM.PlantRoomSizer.CurvePoint", "X" : 370.0, "Y" : 2.9403409090909092 }, { "_t" : "BH.oM.PlantRoomSizer.CurvePoint", "X" : 480.0, "Y" : 2.9403409090909092 }, { "_t" : "BH.oM.PlantRoomSizer.CurvePoint", "X" : 620.0, "Y" : 2.9261363636363638 }, { "_t" : "BH.oM.PlantRoomSizer.CurvePoint", "X" : 800.0, "Y" : 3.1107954545454546 }, { "_t" : "BH.oM.PlantRoomSizer.CurvePoint", "X" : 1020.0, "Y" : 3.28125 }, { "_t" : "BH.oM.PlantRoomSizer.CurvePoint", "X" : 1280.0, "Y" : 3.3096590909090908 }, { "_t" : "BH.oM.PlantRoomSizer.CurvePoint", "X" : 1580.0, "Y" : 3.5511363636363633 }, { "_t" : "BH.oM.PlantRoomSizer.CurvePoint", "X" : 1940.0, "Y" : 3.7073863636363633 }, { "_t" : "BH.oM.PlantRoomSizer.CurvePoint", "X" : 2400.0, "Y" : 4.1051136363636358 }, { "_t" : "BH.oM.PlantRoomSizer.CurvePoint", "X" : 2700.0, "Y" : 4.3181818181818183 }, { "_t" : "BH.oM.PlantRoomSizer.CurvePoint", "X" : 3800.0, "Y" : 4.5170454545454541 }, { "_t" : "BH.oM.PlantRoomSizer.CurvePoint", "X" : 5000.0, "Y" : 4.6590909090909092 }, { "_t" : "BH.oM.PlantRoomSizer.CurvePoint", "X" : 6100.0, "Y" : 4.7727272727272725 }, { "_t" : "BH.oM.PlantRoomSizer.CurvePoint", "X" : 7400.0, "Y" : 5.1420454545454541 }, { "_t" : "BH.oM.PlantRoomSizer.CurvePoint", "X" : 8400.0, "Y" : 5.4261363636363633 }, { "_t" : "BH.oM.PlantRoomSizer.CurvePoint", "X" : 10400.0, "Y" : 5.5113636363636358 }, { "_t" : "BH.oM.PlantRoomSizer.CurvePoint", "X" : 13000.0, "Y" : 5.639204545454545 }, { "_t" : "BH.oM.PlantRoomSizer.CurvePoint", "X" : 15400.0, "Y" : 6.1789772727272725 }, { "_t" : "BH.oM.PlantRoomSizer.CurvePoint", "X" : 18600.0, "Y" : 6.3210227272727266 }, { "_t" : "BH.oM.PlantRoomSizer.CurvePoint", "X" : 22400.0, "Y" : 6.4488636363636358 }, { "_t" : "BH.oM.PlantRoomSizer.CurvePoint", "X" : 25200.0, "Y" : 6.6335227272727266 }, { "_t" : "BH.oM.PlantRoomSizer.CurvePoint", "X" : 29400.0, "Y" : 6.7471590909090908 }, { "_t" : "BH.oM.PlantRoomSizer.CurvePoint", "X" : 32800.0, "Y" : 6.875 }, { "_t" : "BH.oM.PlantRoomSizer.CurvePoint", "X" : 38400.0, "Y" : 7.0170454545454541 }], "BHoM_Guid" : "3c57695f-bfeb-4366-ade6-344993714bef", "_bhomVersion" : "6.3" }