{ "_t" : "BH.oM.PlantRoomSizer.DataSeries", "DataPoints" : [{ "_t" : "BH.oM.PlantRoomSizer.CurvePoint", "X" : 22.805429864253391, "Y" : 2.2000000000000002 }, { "_t" : "BH.oM.PlantRoomSizer.CurvePoint", "X" : 45.610859728506782, "Y" : 2.5 }, { "_t" : "BH.oM.PlantRoomSizer.CurvePoint", "X" : 68.41628959276018, "Y" : 2.5 }, { "_t" : "BH.oM.PlantRoomSizer.CurvePoint", "X" : 93.393665158371036, "Y" : 3.0 }, { "_t" : "BH.oM.PlantRoomSizer.CurvePoint", "X" : 287.78280542986425, "Y" : 3.0 }, { "_t" : "BH.oM.PlantRoomSizer.CurvePoint", "X" : 348.59728506787326, "Y" : 4.0 }, { "_t" : "BH.oM.PlantRoomSizer.CurvePoint", "X" : 1099.0045248868778, "Y" : 4.0 }], "BHoM_Guid" : "04bf3994-f3fa-4215-a18c-bdf5f9c4aec1", "_bhomVersion" : "6.3" }